pypopulation/__init__.py
pypopulation/implementation.py
pypopulation/resources/countries.json
pypopulation-2020.3.dist-info/LICENSE
pypopulation-2020.3.dist-info/WHEEL
pypopulation-2020.3.dist-info/METADATA
pypopulation-2020.3.dist-info/RECORD
