Metadata-Version: 2.1
Name: pypopulation
Version: 2020.3
Summary: Population lookup via ISO 3166 country codes
Home-page: https://github.com/kwzrd/pypopulation
License: MIT
Keywords: country,population,ISO 3166
Author: kwzrd
Author-email: kay.wzrd@gmail.com
Requires-Python: >=3.6.1,<4.0.0
Classifier: License :: OSI Approved :: MIT License
Classifier: Programming Language :: Python :: 3
Classifier: Programming Language :: Python :: 3.7
Classifier: Programming Language :: Python :: 3.8
Classifier: Programming Language :: Python :: 3.9
Project-URL: Repository, https://github.com/kwzrd/pypopulation
